odoo_module_un_install/__init__.py
odoo_module_un_install/exceptions.py
odoo_module_un_install/odoo_connection.py
odoo_module_un_install/odoo_module_un_install.py
odoo_module_un_install/secure_login.py
odoo_module_un_install/utils.py
odoo_module_un_install/version.py
odoo_module_un_install_equitania-1.1.7.dist-info/licenses/LICENSE.txt
odoo_module_un_install_equitania-1.1.7.dist-info/METADATA
odoo_module_un_install_equitania-1.1.7.dist-info/WHEEL
odoo_module_un_install_equitania-1.1.7.dist-info/entry_points.txt
odoo_module_un_install_equitania-1.1.7.dist-info/top_level.txt
odoo_module_un_install_equitania-1.1.7.dist-info/RECORD
