Metadata-Version: 2.4
Name: odoo-module-un-install-equitania
Version: 1.1.7
Summary: A package to un/install modules in Odoo
Author: Equitania Software GmbH
Author-email: info@equitania.de
Classifier: Development Status :: 5 - Production/Stable
Classifier: Programming Language :: Python :: 3
Classifier: Programming Language :: Python :: 3.8
Classifier: Programming Language :: Python :: 3.9
Classifier: Programming Language :: Python :: 3.10
Classifier: Programming Language :: Python :: 3.11
Classifier: Programming Language :: Python :: 3.12
Classifier: License :: OSI Approved :: GNU Affero General Public License v3
Classifier: Operating System :: OS Independent
Classifier: Intended Audience :: Developers
Classifier: Topic :: Software Development :: Libraries :: Python Modules
Requires-Python: >=3.8
License-File: LICENSE.txt
Requires-Dist: OdooRPC>=0.10.1
Requires-Dist: click>=8.1.8
Requires-Dist: PyYaml>=6.0.2
Requires-Dist: python-dotenv>=1.0.0
Requires-Dist: colorama>=0.4.4
Requires-Dist: tqdm>=4.62.0
Requires-Dist: keyring>=23.0.0
Requires-Dist: python-dateutil>=2.8.2
Dynamic: author
Dynamic: author-email
Dynamic: classifier
Dynamic: description
Dynamic: description-content-type
Dynamic: license-file
Dynamic: requires-dist
Dynamic: requires-python
Dynamic: summary
